adrmdr/__init__.py
adrmdr/adrmdr.py
adrmdr/def.py
adrmdr-0.2.1.dist-info/LICENSE
adrmdr-0.2.1.dist-info/METADATA
adrmdr-0.2.1.dist-info/WHEEL
adrmdr-0.2.1.dist-info/entry_points.txt
adrmdr-0.2.1.dist-info/top_level.txt
adrmdr-0.2.1.dist-info/RECORD
